Nxpy-0.6.0.dist-info/METADATA
Nxpy-0.6.0.dist-info/RECORD
Nxpy-0.6.0.dist-info/WHEEL
Nxpy-0.6.0.dist-info/top_level.txt
nxpy/__init__.py
nxpy/ccase/__init__.py
nxpy/ccase/cleartool.py
nxpy/ccase/test/__init__.py
nxpy/ccase/test/env.py
nxpy/command/__init__.py
nxpy/command/command.py
nxpy/command/error.py
nxpy/command/interpreter.py
nxpy/command/option.py
nxpy/core/__init__.py
nxpy/core/abstract.py
nxpy/core/async_subprocess.py
nxpy/core/backup_file.py
nxpy/core/error.py
nxpy/core/file.py
nxpy/core/file_object.py
nxpy/core/memo.py
nxpy/core/past.py
nxpy/core/path.py
nxpy/core/sequence.py
nxpy/core/sort.py
nxpy/core/temp_file.py
nxpy/core/_impl/__init__.py
nxpy/core/_impl/log.py
nxpy/etree/__init__.py
nxpy/etree/util.py
nxpy/maven/__init__.py
nxpy/maven/artifact.py
nxpy/maven/assembly_descriptor.py
nxpy/maven/mvn.py
nxpy/maven/pom.py
nxpy/msvs/__init__.py
nxpy/msvs/assembly_info.py
nxpy/msvs/project.py
nxpy/msvs/solution.py
nxpy/msvs/_impl/__init__.py
nxpy/msvs/_impl/solution/__init__.py
nxpy/msvs/_impl/solution/ast.py
nxpy/msvs/_impl/solution/parser.py
nxpy/msvs/_impl/solution/parsetab.py
nxpy/msvs/_impl/solution/scanner.py
nxpy/ply/__init__.py
nxpy/ply/parser.py
nxpy/ply/scanner.py
nxpy/scons/__init__.py
nxpy/scons/clean_action.py
nxpy/scons/msvs.py
nxpy/scons/project.py
nxpy/scons/util.py
nxpy/svn/__init__.py
nxpy/svn/svn.py
nxpy/svn/svnadmin.py
nxpy/svn/url.py
nxpy/svn/wcopy.py
nxpy/test/__init__.py
nxpy/test/env.py
nxpy/test/log.py
nxpy/test/test.py
nxpy/wx/__init__.py
nxpy/wx/interpreter.py
nxpy/wx/test/__init__.py
nxpy/wx/test/interpreter_test.py
nxpy/xml/__init__.py
nxpy/xml/util.py
