Metadata-Version: 2.1
Name: Nxpy
Version: 0.6.0
Summary: Nick's Python Toolchest
Home-page: http://nxpy.sourceforge.net
Author: Nicola Musatti
Author-email: nmusatti@users.sf.net
License: Boost Software License version 1.0
Platform: UNKNOWN
Classifier: Development Status :: 4 - Beta
Classifier: Intended Audience :: Developers
Classifier: License :: OSI Approved
Classifier: Programming Language :: Python :: 2
Classifier: Programming Language :: Python :: 2.6
Classifier: Programming Language :: Python :: 2.7
Classifier: Programming Language :: Python :: 3
Classifier: Programming Language :: Python :: 3.3
Classifier: Programming Language :: Python :: 3.4
Classifier: Programming Language :: Python :: 3.5
Classifier: Programming Language :: Python :: 3.6
Classifier: Topic :: Software Development :: Libraries
Requires-Dist: six (>=1.8.0)
